filters_iso/__init__.py
filters_iso-1.0.3.dist-info/DESCRIPTION.rst
filters_iso-1.0.3.dist-info/METADATA
filters_iso-1.0.3.dist-info/RECORD
filters_iso-1.0.3.dist-info/WHEEL
filters_iso-1.0.3.dist-info/entry_points.txt
filters_iso-1.0.3.dist-info/metadata.json
filters_iso-1.0.3.dist-info/top_level.txt
