Metadata-Version: 2.0
Name: filters-iso
Version: 1.0.3
Summary: Adds filters for interpreting ISO codes.
Home-page: https://filters.readthedocs.io/
Author: Phoenix Zerin
Author-email: phoenix.zerin@eflglobal.com
License: MIT
Keywords: data validation,iso-3166,iso-4217,ietf language tags,bcp 47
Platform: UNKNOWN
Classifier: Development Status :: 5 - Production/Stable
Classifier: Intended Audience :: Developers
Classifier: License :: OSI Approved :: MIT License
Classifier: Programming Language :: Python :: 2
Classifier: Programming Language :: Python :: 2.7
Classifier: Programming Language :: Python :: 3
Classifier: Programming Language :: Python :: 3.5
Classifier: Programming Language :: Python :: 3.6
Classifier: Topic :: Software Development :: Libraries :: Python Modules
Classifier: Topic :: Text Processing :: Filters
Requires-Dist: filters (>=1.2.0)
Requires-Dist: iso3166
Requires-Dist: language-tags
Requires-Dist: py-moneyed
